server/__init__.py
server/decorators.py
server/descriptors.py
server/err.py
server/metaclasses.py
server/server.py
server/common/__init__.py
server/common/utils.py
server/common/variables.py
server/documents/__init__.py
server/documents/source/__init__.py
server/documents/source/conf.py
server/log/__init__.py
server/log/client_log_config.py
server/log/server_log_config.py
server/server/__init__.py
server/server/add_user.py
server/server/config_window.py
server/server/core.py
server/server/database.py
server/server/main_window.py
server/server/remove_user.py
server/server/stat_window.py
my_first_messager_serv-0.0.1.dist-info/METADATA
my_first_messager_serv-0.0.1.dist-info/WHEEL
my_first_messager_serv-0.0.1.dist-info/top_level.txt
my_first_messager_serv-0.0.1.dist-info/RECORD
