Metadata-Version: 2.1
Name: my-first-messager-serv
Version: 0.0.1
Summary: part server
Home-page: UNKNOWN
Author: Pentegov Dmitriy
Author-email: pentegov_92@mail.ru
License: UNKNOWN
Platform: UNKNOWN
Requires-Dist: PyQt5
Requires-Dist: sqlalchemy
Requires-Dist: pycryptodome
Requires-Dist: pycryptodomex
